xueshanlinghu
