Metadata-Version: 1.1
Name: xueshanlinghu
Version: 1.2.5
Summary: this is a package created by xueshanlinghu tutor. Now including math class.
Home-page: https://github.com/xueshanlinghu/xueshanlinghu-package.git
Author: xueshanlinghu
Author-email: xueshanlinghu@xueshanlinghu.com
License: MIT
Keywords: xueshanlinghu python package math
Platform: UNKNOWN
Classifier: License :: OSI Approved :: MIT License
Classifier: Programming Language :: Python
Classifier: Intended Audience :: Developers
Classifier: Operating System :: OS Independent
